.gitignore
LICENSE.txt
MANIFEST.in
README.md
setup.cfg
setup.py
docs/.nojekyll
docs/Makefile
docs/index.html
docs/make.bat
docs/source/api.rst
docs/source/conf.py
docs/source/doc.py
docs/source/index.rst
docs/source/introduction.rst
docs/source/.ipynb_checkpoints/test_nb-checkpoint.ipynb
docs/source/_static/style copy.css
docs/source/_static/style.css
docs/source/_static/style.css.backup
docs/source/_templates/class.rst
docs/source/_templates/layout.html
docs/source/_templates/numpydoc_docstring.rst
docs/source/_templates/page.html
docs/source/guides/PCEReg_guide.rst
docs/source/tutorials/tutorial01_files/tutorial01_24_1.png
docs/source/tutorials/tutorial01_files/tutorial01_6_1.png
docs/source/tutorials/tutorial01_files/tutorial01_7_1.png
docs/source/tutorials/tutorial02_files/tutorial02_5_1.png
tesuract/__init__.py
tesuract/experimental.py
tesuract/multiindex.py
tesuract/pce.py
tesuract/pce_multitarget_regression.py
tesuract/preprocessing.py
tesuract/quadrature.py
tesuract/utils.py
tesuract.egg-info/PKG-INFO
tesuract.egg-info/SOURCES.txt
tesuract.egg-info/dependency_links.txt
tesuract.egg-info/not-zip-safe
tesuract.egg-info/requires.txt
tesuract.egg-info/top_level.txt
tesuract/sandbox/heat_flux_regression_test.py.orig
tesuract/sandbox/multitarget_reg_test.py
tesuract/sandbox/pce_development.py
tesuract/sandbox/pce_jax.py
tesuract/sandbox/pce_jax_scipy.py
tesuract/sandbox/pce_jax_test.py
tesuract/sandbox/pce_multitarget_regression2.py
tesuract/sandbox/pceregression.py
tesuract/sandbox/quadrature_new.py
tesuract/sandbox/quadrature_old.py
tesuract/sandbox/scaler_test.py
tesuract/sandbox/speed_test.py
tesuract/sandbox/temp.py
tesuract/sandbox/test.py
tesuract/sandbox/wrapper_test.py
tesuract/sandbox/wrapper_test_w_umap.py
tesuract/sandbox/x_opt2_unscaled.txt
tesuract/sandbox/x_opt_unscaled.txt
tesuract/tests/__init__.py
tesuract/tests/test_multiindex.py
tesuract/tests/test_pcebuilder.py
tesuract/tests/test_pceregression.py
tesuract/tests/test_pceregression2.py
tesuract/tests/test_preprocessing.py
tesuract/tests/test_quadrature.py
tesuract/tests/test_regression_w_cv.py
tesuract/tests/data/X_2dquad_points.txt
tesuract/tests/data/X_train_ESM.txt
